[{"city": {"url": "/perth-australia", "name": "Perth", "slug": "perth-australia"}, "name": "Spacecubed Coworking Perth", "img": "https://sharedesk.net/api/httpdocs/media/workspaces/6c/1d/a8/6c1da886822c67822bcf3679d04369fa-medium.jpg", "price_per_day_in_usd": 7, "url": "https://www.sharedesk.net/spaces/view/581/spacecubed-coworking-perth/", "country": {"url": "/countries/australia", "name": "Australia", "slug": "australia"}, "price": {"USD": 7, "AUD": 9}, "location": {"latitude": -31.949001, "longitude": 115.860466}, "distance_from_center_in_km": 0.59647921488165, "type": "coworking", "slug": "spacecubed-coworking-perth-ground-floor-perth", "user": {"distance": {"mi": 0, "km": 0}}}, {"city": {"url": "/perth-australia", "name": "Perth", "slug": "perth-australia"}, "name": "Spacecubed", "img": "https://coworker-media.s3.amazonaws.com/photos/australia/perth/spacecubed/main.jpg", "price_per_day_in_usd": 7, "url": "https://www.coworker.com/australia/perth/spacecubed", "country": {"url": "/countries/australia", "name": "Australia", "slug": "australia"}, "price": {"USD": 7, "AUD": 10}, "location": {"latitude": -31.9553031, "longitude": 115.8578339}, "distance_from_center_in_km": 0.21242013204635, "type": "coworking", "slug": "spacecubed-45-st-georges-terrace-perth-western-australia-perth", "user": {"distance": {"mi": 0, "km": 0}}}, {"city": {"url": "/perth-australia", "name": "Perth", "slug": "perth-australia"}, "name": "Fspace", "img": "https://sharedesk.net/api/httpdocs/media/workspaces/01/de/d4/01ded4259d101feb739b06c399e9cd9c-medium.jpg", "price_per_day_in_usd": 8, "url": "https://www.sharedesk.net/spaces/view/5051/fspace/", "country": {"url": "/countries/australia", "name": "Australia", "slug": "australia"}, "price": {"USD": 8, "AUD": 10}, "location": {"latitude": -32.053802, "longitude": 115.745811}, "distance_from_center_in_km": 15.309384693178, "type": "coworking", "slug": "fspace-27-market-street-perth", "user": {"distance": {"mi": 9, "km": 15}}}, {"city": {"url": "/perth-australia", "name": "Perth", "slug": "perth-australia"}, "name": "Claisebrook Design Community", "img": "https://coworker-media.s3.amazonaws.com/photos/australia/perth/claisebrook-design-community/main.jpeg", "price_per_day_in_usd": 8, "url": "https://www.coworker.com/australia/perth/claisebrook-design-community", "country": {"url": "/countries/australia", "name": "Australia", "slug": "australia"}, "price": {"USD": 8, "AUD": 11}, "location": {"latitude": -31.947479, "longitude": 115.871568}, "distance_from_center_in_km": 1.5255207326108, "type": "coworking", "slug": "claisebrook-design-community-25-gladstone-street-perth-wa-perth", "user": {"distance": {"mi": 0.6, "km": 1}}}, {"city": {"url": "/perth-australia", "name": "Perth", "slug": "perth-australia"}, "name": "Sync Labs", "img": "https://sharedesk.net/api/httpdocs/media/workspaces/69/f6/5a/69f65a2e91e6051a23abe7293bf3386a-medium.jpg", "price_per_day_in_usd": 11, "url": "https://www.sharedesk.net/spaces/view/3388/sync-labs/", "country": {"url": "/countries/australia", "name": "Australia", "slug": "australia"}, "price": {"USD": 11, "AUD": 15}, "location": {"latitude": -31.93845, "longitude": 115.842117}, "distance_from_center_in_km": 2.1885944903443, "type": "coworking", "slug": "sync-labs-663-newcastle-street-perth", "user": {"distance": {"mi": 1.2, "km": 2}}}, {"city": {"url": "/perth-australia", "name": "Perth", "slug": "perth-australia"}, "name": "City Hive", "img": "https://coworker-media.s3.amazonaws.com/photos/australia/perth/city-hive/main.jpg", "price_per_day_in_usd": 11, "url": "https://www.coworker.com/australia/perth/city-hive", "country": {"url": "/countries/australia", "name": "Australia", "slug": "australia"}, "price": {"USD": 11, "AUD": 15}, "location": {"latitude": -31.953513, "longitude": 115.857047}, "distance_from_center_in_km": 2.4157503266135e-05, "type": "coworking", "slug": "city-hive-184-marine-terrace-geraldton-perth-western-australia-perth", "user": {"distance": {"mi": 0, "km": 0}}}, {"city": {"url": "/perth-australia", "name": "Perth", "slug": "perth-australia"}, "name": "The Creative Arts House", "img": "https://coworker-media.s3.amazonaws.com/photos/australia/perth/the-creative-arts-house/main.jpg", "price_per_day_in_usd": 11, "url": "https://www.coworker.com/australia/perth/the-creative-arts-house", "country": {"url": "/countries/australia", "name": "Australia", "slug": "australia"}, "price": {"USD": 11, "AUD": 15}, "location": {"latitude": -31.9389408, "longitude": 115.8564782}, "distance_from_center_in_km": 1.6212657949414, "type": "coworking", "slug": "the-creative-arts-house-upper-level-243-fitzgerald-street-perth", "user": {"distance": {"mi": 0.6, "km": 1}}}, {"city": {"url": "/perth-australia", "name": "Perth", "slug": "perth-australia"}, "name": "HIVE by Liberty", "img": "https://coworker-media.s3.amazonaws.com/photos/australia/perth/hive-by-liberty/main.jpg", "price_per_day_in_usd": 12, "url": "https://www.coworker.com/australia/perth/hive-by-liberty", "country": {"url": "/countries/australia", "name": "Australia", "slug": "australia"}, "price": {"USD": 12, "AUD": 16}, "location": {"latitude": -31.955504, "longitude": 115.85818}, "distance_from_center_in_km": 0.24581996599399, "type": "coworking", "slug": "hive-by-liberty-77-st-georges-terrace-perth", "user": {"distance": {"mi": 0, "km": 0}}}, {"city": {"url": "/perth-australia", "name": "Perth", "slug": "perth-australia"}, "name": "The West Perth Office", "img": "https://coworker-media.s3.amazonaws.com/photos/australia/perth/the-west-perth-office/main.JPG", "price_per_day_in_usd": 12, "url": "https://www.coworker.com/australia/perth/the-west-perth-office", "country": {"url": "/countries/australia", "name": "Australia", "slug": "australia"}, "price": {"USD": 12, "AUD": 16}, "location": {"latitude": -31.946668, "longitude": 115.842158}, "distance_from_center_in_km": 1.5977403964462, "type": "coworking", "slug": "the-west-perth-office-8-clive-street-bicton-perth", "user": {"distance": {"mi": 0.6, "km": 1}}}, {"city": {"url": "/perth-australia", "name": "Perth", "slug": "perth-australia"}, "name": "Synclabs", "img": "https://coworker-media.s3.amazonaws.com/photos/australia/perth/synclabs/main.jpg", "price_per_day_in_usd": 14, "url": "https://www.coworker.com/australia/perth/synclabs", "country": {"url": "/countries/australia", "name": "Australia", "slug": "australia"}, "price": {"USD": 14, "AUD": 18}, "location": {"latitude": -31.93805, "longitude": 115.84197}, "distance_from_center_in_km": 2.2316362118342, "type": "coworking", "slug": "synclabs-unit-6-663-newcastle-street-leederville-western-australia-perth", "user": {"distance": {"mi": 1.2, "km": 2}}}, {"city": {"url": "/perth-australia", "name": "Perth", "slug": "perth-australia"}, "name": "Atomic Sky Tech Hub", "img": "https://sharedesk.net/api/httpdocs/media/workspaces/c2/e0/6e/c2e06e9a80370952f6ec5463c77cbace-medium.jpg", "price_per_day_in_usd": 15, "url": "https://www.sharedesk.net/spaces/view/3717/atomic-sky-tech-hub/", "country": {"url": "/countries/australia", "name": "Australia", "slug": "australia"}, "price": {"USD": 15, "AUD": 20}, "location": {"latitude": -31.9464, "longitude": 115.862}, "distance_from_center_in_km": 0.91868385701048, "type": "coworking", "slug": "atomic-sky-tech-hub-4-money-street-northbridge-perth", "user": {"distance": {"mi": 0, "km": 0}}}, {"city": {"url": "/perth-australia", "name": "Perth", "slug": "perth-australia"}, "name": "Ootb Collective", "img": "https://sharedesk.net/api/httpdocs/media/workspaces/d2/8a/30/d28a3097fa7cf63ad01c4f328314e2f2-medium.jpg", "price_per_day_in_usd": 16, "url": "https://www.sharedesk.net/spaces/view/6882/ootb-collective/", "country": {"url": "/countries/australia", "name": "Australia", "slug": "australia"}, "price": {"USD": 16, "AUD": 22}, "location": {"latitude": -31.995495, "longitude": 115.762863}, "distance_from_center_in_km": 10.035708518191, "type": "coworking", "slug": "ootb-collective-15-vera-street-perth", "user": {"distance": {"mi": 6, "km": 10}}}, {"city": {"url": "/perth-australia", "name": "Perth", "slug": "perth-australia"}, "name": "Tech Hub", "img": "https://coworker-media.s3.amazonaws.com/photos/australia/perth/tech-hub/main.jpeg", "price_per_day_in_usd": 16, "url": "https://www.coworker.com/australia/perth/tech-hub", "country": {"url": "/countries/australia", "name": "Australia", "slug": "australia"}, "price": {"USD": 16, "AUD": 22}, "location": {"latitude": -31.9463798, "longitude": 115.8625384}, "distance_from_center_in_km": 0.94741506033663, "type": "coworking", "slug": "tech-hub-4-money-street-perth", "user": {"distance": {"mi": 0, "km": 0}}}, {"city": {"url": "/perth-australia", "name": "Perth", "slug": "perth-australia"}, "name": "Nestspace Businesss Hub", "img": "https://sharedesk.net/api/httpdocs/media/workspaces/39/d4/b5/39d4b545fb02556829aab1db805021c3-medium.jpg", "price_per_day_in_usd": 17, "url": "https://www.sharedesk.net/spaces/view/2804/nestspace-businesss-hub/", "country": {"url": "/countries/australia", "name": "Australia", "slug": "australia"}, "price": {"USD": 17, "AUD": 23}, "location": {"latitude": -31.953512, "longitude": 115.857048}, "distance_from_center_in_km": 0.00015816010599596, "type": "coworking", "slug": "nestspace-businesss-hub-the-business-building-328-albany-highway-victoria-park-perth", "user": {"distance": {"mi": 0, "km": 0}}}, {"city": {"url": "/perth-australia", "name": "Perth", "slug": "perth-australia"}, "name": "105 Sgt", "img": "https://sharedesk.net/api/httpdocs/media/workspaces/48/65/3a/48653af2e798bc96b6ef0b76d8a02139-medium.jpg", "price_per_day_in_usd": 19, "url": "https://www.sharedesk.net/spaces/view/4038/105-sgt/", "country": {"url": "/countries/australia", "name": "Australia", "slug": "australia"}, "price": {"USD": 19, "AUD": 25}, "location": {"latitude": -31.955231, "longitude": 115.856819}, "distance_from_center_in_km": 0.19221911006894, "type": "coworking", "slug": "105-sgt-level-3-105-st-georges-terrace-perth", "user": {"distance": {"mi": 0, "km": 0}}}, {"city": {"url": "/perth-australia", "name": "Perth", "slug": "perth-australia"}, "name": "Minespace", "img": "https://sharedesk.net/api/httpdocs/media/workspaces/98/23/c9/9823c9091899dc6f227f9133ba2dfd30-medium.jpg", "price_per_day_in_usd": 19, "url": "https://www.sharedesk.net/spaces/view/4994/minespace/", "country": {"url": "/countries/australia", "name": "Australia", "slug": "australia"}, "price": {"USD": 19, "AUD": 26}, "location": {"latitude": -31.947836, "longitude": 115.839859}, "distance_from_center_in_km": 1.7402224589743, "type": "coworking", "slug": "minespace-level-1-1292-hay-street-perth", "user": {"distance": {"mi": 0.6, "km": 1}}}, {"city": {"url": "/perth-australia", "name": "Perth", "slug": "perth-australia"}, "name": "FLUX", "img": "https://coworker-media.s3.amazonaws.com/photos/australia/perth/flux/main.jpg", "price_per_day_in_usd": 0, "url": "https://www.coworker.com/australia/perth/flux", "country": {"url": "/countries/australia", "name": "Australia", "slug": "australia"}, "location": {"latitude": -31.9556748, "longitude": 115.8590516}, "distance_from_center_in_km": 0.30583815593968, "type": "coworking", "slug": "flux-191-st-georges-terrace-perth"}]