[{"city": {"url": "/", "name": "", "slug": ""}, "name": "Kelowna Okanagan Lake", "img": "http://aff.bstatic.com/images/hotel/max500/595/59580487.jpg", "price_per_day_in_usd": 22, "url": "http://www.booking.com/hotel/ca/kelowna-okanagan-lake.html", "country": {"url": "/countries/", "name": "", "slug": ""}, "price": {"USD": 22, "CAD": 30}, "location": {"latitude": 49.886425864416, "longitude": -119.48759525033}, "distance_from_center_in_km": 0.62631953957971, "type": "hotel", "slug": "kelowna-okanagan-lake-kelowna", "user": {"distance": {"mi": 0, "km": 0}}}, {"city": {"url": "/", "name": "", "slug": ""}, "name": "UBC Okanagan Campus", "img": "http://aff.bstatic.com/images/hotel/max500/380/3801577.jpg", "price_per_day_in_usd": 37, "url": "http://www.booking.com/hotel/ca/ubc-okanagan-campus.html", "country": {"url": "/countries/", "name": "", "slug": ""}, "price": {"USD": 37, "CAD": 50}, "location": {"latitude": 49.942457024913, "longitude": -119.39634561539}, "distance_from_center_in_km": 9.362460208931, "type": "hotel", "slug": "ubc-okanagan-campus-kelowna", "user": {"distance": {"mi": 5.4, "km": 9}}}, {"city": {"url": "/", "name": "", "slug": ""}, "name": "Mission Park Inn", "img": "http://aff.bstatic.com/images/hotel/max500/422/4227368.jpg", "price_per_day_in_usd": 53, "url": "http://www.booking.com/hotel/ca/mission-park-inn.html", "country": {"url": "/countries/", "name": "", "slug": ""}, "price": {"USD": 53, "CAD": 71}, "location": {"latitude": 49.856623655592, "longitude": -119.49083715677}, "distance_from_center_in_km": 3.5032157498987, "type": "hotel", "slug": "mission-park-inn-kelowna", "user": {"distance": {"mi": 1.8, "km": 3}}}, {"city": {"url": "/", "name": "", "slug": ""}, "name": "PineWood Guesthouse", "img": "http://aff.bstatic.com/images/hotel/max500/597/59730238.jpg", "price_per_day_in_usd": 56, "url": "http://www.booking.com/hotel/ca/pinewood-bed-and-breakfast.html", "country": {"url": "/countries/", "name": "", "slug": ""}, "price": {"USD": 56, "CAD": 75}, "location": {"latitude": 49.787230162985, "longitude": -119.72829580307}, "distance_from_center_in_km": 20.073380976535, "type": "hotel", "slug": "pinewood-guesthouse-peachland", "user": {"distance": {"mi": 12, "km": 20}}}, {"city": {"url": "/", "name": "", "slug": ""}, "name": "Oasis Inn", "img": "http://aff.bstatic.com/images/hotel/max500/321/32109620.jpg", "price_per_day_in_usd": 59, "url": "http://www.booking.com/hotel/ca/chinook-and-oasis-motel.html", "country": {"url": "/countries/", "name": "", "slug": ""}, "price": {"USD": 59, "CAD": 79}, "location": {"latitude": 49.880277147038, "longitude": -119.47729736566}, "distance_from_center_in_km": 1.5893005724233, "type": "hotel", "slug": "oasis-inn-kelowna", "user": {"distance": {"mi": 0.6, "km": 1}}}, {"city": {"url": "/", "name": "", "slug": ""}, "name": "Super 8 Lake Country - Winfield Area", "img": "http://aff.bstatic.com/images/hotel/max500/733/73321109.jpg", "price_per_day_in_usd": 64, "url": "http://www.booking.com/hotel/ca/super-8-lake-country-winfield-area.html", "country": {"url": "/countries/", "name": "", "slug": ""}, "price": {"USD": 64, "CAD": 85}, "location": {"latitude": 50.020522836455, "longitude": -119.40649107099}, "distance_from_center_in_km": 16.072354933213, "type": "hotel", "slug": "super-8-lake-country-winfield-area-winfield-ca", "user": {"distance": {"mi": 9.6, "km": 16}}}, {"city": {"url": "/", "name": "", "slug": ""}, "name": "Okanagan Seasons Resort", "img": "http://aff.bstatic.com/images/hotel/max500/185/18562822.jpg", "price_per_day_in_usd": 66, "url": "http://www.booking.com/hotel/ca/okanagan-seasons-resort.html", "country": {"url": "/countries/", "name": "", "slug": ""}, "price": {"USD": 66, "CAD": 88}, "location": {"latitude": 49.889749470387, "longitude": -119.41817879677}, "distance_from_center_in_km": 5.5794383278606, "type": "hotel", "slug": "okanagan-seasons-resort-kelowna", "user": {"distance": {"mi": 3, "km": 5}}}, {"city": {"url": "/", "name": "", "slug": ""}, "name": "Lake Country Inn", "img": "http://aff.bstatic.com/images/hotel/max500/408/4084646.jpg", "price_per_day_in_usd": 67, "url": "http://www.booking.com/hotel/ca/lake-country-inn.html", "country": {"url": "/countries/", "name": "", "slug": ""}, "price": {"USD": 67, "CAD": 89}, "location": {"latitude": 50.027593240187, "longitude": -119.40532565117}, "distance_from_center_in_km": 16.828140349913, "type": "hotel", "slug": "lake-country-inn-winfield-ca", "user": {"distance": {"mi": 9.6, "km": 16}}}, {"city": {"url": "/", "name": "", "slug": ""}, "name": "Canadas Best Value Inn Kelowna", "img": "http://aff.bstatic.com/images/hotel/max500/450/4504240.jpg", "price_per_day_in_usd": 67, "url": "http://www.booking.com/hotel/ca/canadas-best-value-inn-kelowna.html", "country": {"url": "/countries/", "name": "", "slug": ""}, "price": {"USD": 67, "CAD": 89}, "location": {"latitude": 49.894452969428, "longitude": -119.41458463669}, "distance_from_center_in_km": 5.8776802407242, "type": "hotel", "slug": "canadas-best-value-inn-kelowna-kelowna", "user": {"distance": {"mi": 3, "km": 5}}}, {"city": {"url": "/kelowna-canada", "name": "Kelowna", "slug": "kelowna-canada"}, "name": "SameSun Kelowna", "img": "http://ucd.hwstatic.com/propertyimages/1/1831/11.jpg", "price_per_day_in_usd": 67, "url": "http://www.hostelworld.com/hosteldetails.php/SameSun-Kelowna/Kelowna/1831", "country": {"url": "/countries/canada", "name": "Canada", "slug": "canada"}, "price": {"USD": 67, "CAD": 89}, "location": {"latitude": 49.8832982, "longitude": -119.4991493}, "distance_from_center_in_km": 0.564216185101, "type": "hotel", "slug": "samesun-kelowna-245-harvey-ave-kelowna-bc-kelowna-kelowna", "user": {"distance": {"mi": 0, "km": 0}}}, {"city": {"url": "/", "name": "", "slug": ""}, "name": "Days Inn Kelowna", "img": "http://aff.bstatic.com/images/hotel/max500/119/11912890.jpg", "price_per_day_in_usd": 69, "url": "http://www.booking.com/hotel/ca/days-inn-kelowna.html", "country": {"url": "/countries/", "name": "", "slug": ""}, "price": {"USD": 69, "CAD": 93}, "location": {"latitude": 49.893811924351, "longitude": -119.41445857287}, "distance_from_center_in_km": 5.8783533972559, "type": "hotel", "slug": "days-inn-kelowna-kelowna", "user": {"distance": {"mi": 3, "km": 5}}}, {"city": {"url": "/", "name": "", "slug": ""}, "name": "Mission Creek Country Inn", "img": "http://aff.bstatic.com/images/hotel/max500/989/9893500.jpg", "price_per_day_in_usd": 71, "url": "http://www.booking.com/hotel/ca/mission-creek-country-inn.html", "country": {"url": "/countries/", "name": "", "slug": ""}, "price": {"USD": 71, "CAD": 95}, "location": {"latitude": 49.851017, "longitude": -119.443928}, "distance_from_center_in_km": 5.5497899889994, "type": "hotel", "slug": "mission-creek-country-inn-kelowna", "user": {"distance": {"mi": 3, "km": 5}}}, {"city": {"url": "/", "name": "", "slug": ""}, "name": "Smith Creek B&B", "img": "http://aff.bstatic.com/images/hotel/max500/232/23240598.jpg", "price_per_day_in_usd": 74, "url": "http://www.booking.com/hotel/ca/smith-creek-b-amp-b.html", "country": {"url": "/countries/", "name": "", "slug": ""}, "price": {"USD": 74, "CAD": 99}, "location": {"latitude": 49.853919068949, "longitude": -119.64201718569}, "distance_from_center_in_km": 11.127046663512, "type": "hotel", "slug": "smith-creek-bb-west-kelowna", "user": {"distance": {"mi": 6.6, "km": 11}}}, {"city": {"url": "/", "name": "", "slug": ""}, "name": "Airport Inn Lakeside", "img": "http://aff.bstatic.com/images/hotel/max500/546/54659301.jpg", "price_per_day_in_usd": 75, "url": "http://www.booking.com/hotel/ca/airport-inn-lakeside.html", "country": {"url": "/countries/", "name": "", "slug": ""}, "price": {"USD": 75, "CAD": 100}, "location": {"latitude": 50.0487162, "longitude": -119.4111039}, "distance_from_center_in_km": 18.879483964015, "type": "hotel", "slug": "airport-inn-lakeside-winfield-ca", "user": {"distance": {"mi": 10.8, "km": 18}}}, {"city": {"url": "/", "name": "", "slug": ""}, "name": "Super 8 West Kelowna", "img": "http://aff.bstatic.com/images/hotel/max500/265/26568625.jpg", "price_per_day_in_usd": 76, "url": "http://www.booking.com/hotel/ca/super-eight-west-kelowna.html", "country": {"url": "/countries/", "name": "", "slug": ""}, "price": {"USD": 76, "CAD": 102}, "location": {"latitude": 49.862192701047, "longitude": -119.58379172779}, "distance_from_center_in_km": 6.9118410079023, "type": "hotel", "slug": "super-8-west-kelowna-west-kelowna", "user": {"distance": {"mi": 3.6, "km": 6}}}, {"city": {"url": "/", "name": "", "slug": ""}, "name": "Wild Nature B&B", "img": "http://aff.bstatic.com/images/hotel/max500/162/16206950.jpg", "price_per_day_in_usd": 78, "url": "http://www.booking.com/hotel/ca/wild-nature-b-amp-b.html", "country": {"url": "/countries/", "name": "", "slug": ""}, "price": {"USD": 78, "CAD": 105}, "location": {"latitude": 49.886174020646, "longitude": -119.24826622009}, "distance_from_center_in_km": 17.750115338912, "type": "hotel", "slug": "wild-nature-bb-kelowna", "user": {"distance": {"mi": 10.2, "km": 17}}}, {"city": {"url": "/", "name": "", "slug": ""}, "name": "Howard Johnson Kelowna", "img": "http://aff.bstatic.com/images/hotel/max500/262/26289828.jpg", "price_per_day_in_usd": 79, "url": "http://www.booking.com/hotel/ca/howard-johnson-kelowna.html", "country": {"url": "/countries/", "name": "", "slug": ""}, "price": {"USD": 79, "CAD": 105}, "location": {"latitude": 49.894440874317, "longitude": -119.41458463669}, "distance_from_center_in_km": 5.8775157088946, "type": "hotel", "slug": "howard-johnson-kelowna-kelowna", "user": {"distance": {"mi": 3, "km": 5}}}, {"city": {"url": "/", "name": "", "slug": ""}, "name": "Siesta Suites", "img": "http://aff.bstatic.com/images/hotel/max500/208/20831276.jpg", "price_per_day_in_usd": 81, "url": "http://www.booking.com/hotel/ca/siesta-inn.html", "country": {"url": "/countries/", "name": "", "slug": ""}, "price": {"USD": 81, "CAD": 108}, "location": {"latitude": 49.86070445888, "longitude": -119.49176385999}, "distance_from_center_in_km": 3.0450229972446, "type": "hotel", "slug": "siesta-suites-kelowna", "user": {"distance": {"mi": 1.8, "km": 3}}}, {"city": {"url": "/", "name": "", "slug": ""}, "name": "Dilworth Inn", "img": "http://aff.bstatic.com/images/hotel/max500/375/37594593.jpg", "price_per_day_in_usd": 81, "url": "http://www.booking.com/hotel/ca/dilworth-inn.html", "country": {"url": "/countries/", "name": "", "slug": ""}, "price": {"USD": 81, "CAD": 109}, "location": {"latitude": 49.882864463095, "longitude": -119.43711787462}, "distance_from_center_in_km": 4.257118666487, "type": "hotel", "slug": "dilworth-inn-kelowna", "user": {"distance": {"mi": 2.4, "km": 4}}}, {"city": {"url": "/", "name": "", "slug": ""}, "name": "Recreation Inn and Suites", "img": "http://aff.bstatic.com/images/hotel/max500/320/32063132.jpg", "price_per_day_in_usd": 81, "url": "http://www.booking.com/hotel/ca/recreation-inn-and-suites.html", "country": {"url": "/countries/", "name": "", "slug": ""}, "price": {"USD": 81, "CAD": 109}, "location": {"latitude": 49.882976801667, "longitude": -119.45508867502}, "distance_from_center_in_km": 2.9835806971641, "type": "hotel", "slug": "recreation-inn-and-suites-kelowna", "user": {"distance": {"mi": 1.2, "km": 2}}}, {"city": {"url": "/", "name": "", "slug": ""}, "name": "Chesterfield Inn", "img": "http://aff.bstatic.com/images/hotel/max500/447/44790233.jpg", "price_per_day_in_usd": 81, "url": "http://www.booking.com/hotel/ca/chesterfield-inn.html", "country": {"url": "/countries/", "name": "", "slug": ""}, "price": {"USD": 81, "CAD": 109}, "location": {"latitude": 49.876933479475, "longitude": -119.49176251888}, "distance_from_center_in_km": 1.2624337641877, "type": "hotel", "slug": "chesterfield-inn-kelowna", "user": {"distance": {"mi": 0.6, "km": 1}}}, {"city": {"url": "/", "name": "", "slug": ""}, "name": "Kokanee Beach Resort", "img": "http://aff.bstatic.com/images/hotel/max500/455/45581887.jpg", "price_per_day_in_usd": 85, "url": "http://www.booking.com/hotel/ca/kokanee-beach-resort.html", "country": {"url": "/countries/", "name": "", "slug": ""}, "price": {"USD": 85, "CAD": 114}, "location": {"latitude": 50.051368731359, "longitude": -119.40645754337}, "distance_from_center_in_km": 19.266843032381, "type": "hotel", "slug": "kokanee-beach-resort-winfield-ca", "user": {"distance": {"mi": 11.4, "km": 19}}}, {"city": {"url": "/", "name": "", "slug": ""}, "name": "Serenity Stay Bed & Breakfast", "img": "http://aff.bstatic.com/images/hotel/max500/727/72709280.jpg", "price_per_day_in_usd": 86, "url": "http://www.booking.com/hotel/ca/serenity-stay-bed-amp-breakfast.html", "country": {"url": "/countries/", "name": "", "slug": ""}, "price": {"USD": 86, "CAD": 115}, "location": {"latitude": 49.845776726952, "longitude": -119.48478877544}, "distance_from_center_in_km": 4.7581353350277, "type": "hotel", "slug": "serenity-stay-bed-breakfast-kelowna", "user": {"distance": {"mi": 2.4, "km": 4}}}, {"city": {"url": "/", "name": "", "slug": ""}, "name": "North Pointe Inn and Suites", "img": "http://aff.bstatic.com/images/hotel/max500/770/77089720.jpg", "price_per_day_in_usd": 89, "url": "http://www.booking.com/hotel/ca/town.html", "country": {"url": "/countries/", "name": "", "slug": ""}, "price": {"USD": 89, "CAD": 119}, "location": {"latitude": 49.892818374048, "longitude": -119.41590696573}, "distance_from_center_in_km": 5.7638853537409, "type": "hotel", "slug": "north-pointe-inn-and-suites-kelowna", "user": {"distance": {"mi": 3, "km": 5}}}, {"city": {"url": "/", "name": "", "slug": ""}, "name": "Kelowna Inn & Suites", "img": "http://aff.bstatic.com/images/hotel/max500/598/59887666.jpg", "price_per_day_in_usd": 89, "url": "http://www.booking.com/hotel/ca/kelowna-inn.html", "country": {"url": "/countries/", "name": "", "slug": ""}, "price": {"USD": 89, "CAD": 119}, "location": {"latitude": 49.88387722908, "longitude": -119.47743147612}, "distance_from_center_in_km": 1.4060848160959, "type": "hotel", "slug": "kelowna-inn-suites-kelowna", "user": {"distance": {"mi": 0.6, "km": 1}}}, {"city": {"url": "/", "name": "", "slug": ""}, "name": "Sandman Hotel & Suites Kelowna", "img": "http://aff.bstatic.com/images/hotel/max500/146/14603025.jpg", "price_per_day_in_usd": 93, "url": "http://www.booking.com/hotel/ca/sandman-suites-kelowna.html", "country": {"url": "/countries/", "name": "", "slug": ""}, "price": {"USD": 93, "CAD": 125}, "location": {"latitude": 49.882395230697, "longitude": -119.44049745798}, "distance_from_center_in_km": 4.0249626251951, "type": "hotel", "slug": "sandman-hotel-suites-kelowna-kelowna", "user": {"distance": {"mi": 2.4, "km": 4}}}, {"city": {"url": "/", "name": "", "slug": ""}, "name": "All Seasons Bed & Breakfast", "img": "http://aff.bstatic.com/images/hotel/max500/720/72037084.jpg", "price_per_day_in_usd": 93, "url": "http://www.booking.com/hotel/ca/all-seasons-bed-breakfast.html", "country": {"url": "/countries/", "name": "", "slug": ""}, "price": {"USD": 93, "CAD": 125}, "location": {"latitude": 49.84837, "longitude": -119.478276}, "distance_from_center_in_km": 4.5811638168829, "type": "hotel", "slug": "all-seasons-bed-breakfast-kelowna", "user": {"distance": {"mi": 2.4, "km": 4}}}, {"city": {"url": "/", "name": "", "slug": ""}, "name": "Casa Loma BnB", "img": "http://aff.bstatic.com/images/hotel/max500/316/31691785.jpg", "price_per_day_in_usd": 93, "url": "http://www.booking.com/hotel/ca/casa-loma-bnb.html", "country": {"url": "/countries/", "name": "", "slug": ""}, "price": {"USD": 93, "CAD": 125}, "location": {"latitude": 49.8582554, "longitude": -119.538415}, "distance_from_center_in_km": 4.4875808621477, "type": "hotel", "slug": "casa-loma-bnb-west-kelowna", "user": {"distance": {"mi": 2.4, "km": 4}}}, {"city": {"url": "/", "name": "", "slug": ""}, "name": "Manteo Resort", "img": "http://aff.bstatic.com/images/hotel/max500/605/60554482.jpg", "price_per_day_in_usd": 96, "url": "http://www.booking.com/hotel/ca/manteo-resort.html", "country": {"url": "/countries/", "name": "", "slug": ""}, "price": {"USD": 96, "CAD": 129}, "location": {"latitude": 49.847246877422, "longitude": -119.4880181551}, "distance_from_center_in_km": 4.5622962995528, "type": "hotel", "slug": "manteo-resort-kelowna", "user": {"distance": {"mi": 2.4, "km": 4}}}, {"city": {"url": "/", "name": "", "slug": ""}, "name": "Super 8 Kelowna", "img": "http://aff.bstatic.com/images/hotel/max500/733/73307044.jpg", "price_per_day_in_usd": 97, "url": "http://www.booking.com/hotel/ca/super-8-kelowna.html", "country": {"url": "/countries/", "name": "", "slug": ""}, "price": {"USD": 97, "CAD": 130}, "location": {"latitude": 49.89247797037, "longitude": -119.41788375378}, "distance_from_center_in_km": 5.6194176052944, "type": "hotel", "slug": "super-8-kelowna-kelowna", "user": {"distance": {"mi": 3, "km": 5}}}, {"city": {"url": "/", "name": "", "slug": ""}, "name": "Lake Okanagan Bed and Breakfast", "img": "http://aff.bstatic.com/images/hotel/max500/287/28708597.jpg", "price_per_day_in_usd": 97, "url": "http://www.booking.com/hotel/ca/lake-okanagan-bed-and-breakfast.html", "country": {"url": "/countries/", "name": "", "slug": ""}, "price": {"USD": 97, "CAD": 130}, "location": {"latitude": 49.844956738599, "longitude": -119.57636100304}, "distance_from_center_in_km": 7.48478947807, "type": "hotel", "slug": "lake-okanagan-bed-and-breakfast-west-kelowna", "user": {"distance": {"mi": 4.2, "km": 7}}}, {"city": {"url": "/", "name": "", "slug": ""}, "name": "Holiday Inn Express Kelowna", "img": "http://aff.bstatic.com/images/hotel/max500/261/26187261.jpg", "price_per_day_in_usd": 99, "url": "http://www.booking.com/hotel/ca/holiday-inn-express-kelowna.html", "country": {"url": "/countries/", "name": "", "slug": ""}, "price": {"USD": 99, "CAD": 132}, "location": {"latitude": 49.885296102686, "longitude": -119.42578554153}, "distance_from_center_in_km": 5.0398025523953, "type": "hotel", "slug": "holiday-inn-express-kelowna-kelowna", "user": {"distance": {"mi": 3, "km": 5}}}, {"city": {"url": "/", "name": "", "slug": ""}, "name": "Comfort Suites Kelowna", "img": "http://aff.bstatic.com/images/hotel/max500/336/33688347.jpg", "price_per_day_in_usd": 100, "url": "http://www.booking.com/hotel/ca/comfort-suites-kelowna.html", "country": {"url": "/countries/", "name": "", "slug": ""}, "price": {"USD": 100, "CAD": 133}, "location": {"latitude": 49.893728985282, "longitude": -119.41667675972}, "distance_from_center_in_km": 5.7194176548248, "type": "hotel", "slug": "comfort-suites-kelowna-kelowna", "user": {"distance": {"mi": 3, "km": 5}}}, {"city": {"url": "/", "name": "", "slug": ""}, "name": "Ramada Hotel and Conference Centre Kelowna", "img": "http://aff.bstatic.com/images/hotel/max500/265/26569780.jpg", "price_per_day_in_usd": 101, "url": "http://www.booking.com/hotel/ca/ramada-and-conference-centre-kelowna.html", "country": {"url": "/countries/", "name": "", "slug": ""}, "price": {"USD": 101, "CAD": 135}, "location": {"latitude": 49.882219807468, "longitude": -119.43876743317}, "distance_from_center_in_km": 4.150443358445, "type": "hotel", "slug": "ramada-hotel-and-conference-centre-kelowna-kelowna", "user": {"distance": {"mi": 2.4, "km": 4}}}, {"city": {"url": "/", "name": "", "slug": ""}, "name": "A Vacation Paradise at Quail Ridge B&B", "img": "http://aff.bstatic.com/images/hotel/max500/119/11997633.jpg", "price_per_day_in_usd": 105, "url": "http://www.booking.com/hotel/ca/quail-ridge-b-amp-b.html", "country": {"url": "/countries/", "name": "", "slug": ""}, "price": {"USD": 105, "CAD": 140}, "location": {"latitude": 49.966838983136, "longitude": -119.40130287412}, "distance_from_center_in_km": 11.086288997315, "type": "hotel", "slug": "a-vacation-paradise-at-quail-ridge-bb-kelowna", "user": {"distance": {"mi": 6.6, "km": 11}}}, {"city": {"url": "/", "name": "", "slug": ""}, "name": "Be and Be Bed & Breakfast", "img": "http://aff.bstatic.com/images/hotel/max500/263/26331425.jpg", "price_per_day_in_usd": 105, "url": "http://www.booking.com/hotel/ca/be-and-be-bed.html", "country": {"url": "/countries/", "name": "", "slug": ""}, "price": {"USD": 105, "CAD": 140}, "location": {"latitude": 49.797305929463, "longitude": -119.49571073055}, "distance_from_center_in_km": 10.079394981653, "type": "hotel", "slug": "be-and-be-bed-breakfast-kelowna", "user": {"distance": {"mi": 6, "km": 10}}}, {"city": {"url": "/", "name": "", "slug": ""}, "name": "Holiday Inn West Kelowna", "img": "http://aff.bstatic.com/images/hotel/max500/373/37380216.jpg", "price_per_day_in_usd": 106, "url": "http://www.booking.com/hotel/ca/west-kelowna-2589-dobbin-road.html", "country": {"url": "/countries/", "name": "", "slug": ""}, "price": {"USD": 106, "CAD": 143}, "location": {"latitude": 49.828880624506, "longitude": -119.63554501533}, "distance_from_center_in_km": 11.966395515728, "type": "hotel", "slug": "holiday-inn-west-kelowna-west-kelowna", "user": {"distance": {"mi": 6.6, "km": 11}}}, {"city": {"url": "/", "name": "", "slug": ""}, "name": "Royal Anne Hotel", "img": "http://aff.bstatic.com/images/hotel/max500/612/61243244.jpg", "price_per_day_in_usd": 111, "url": "http://www.booking.com/hotel/ca/royal-anne.html", "country": {"url": "/countries/", "name": "", "slug": ""}, "price": {"USD": 111, "CAD": 149}, "location": {"latitude": 49.886425468616, "longitude": -119.49572682381}, "distance_from_center_in_km": 0.17094467282886, "type": "hotel", "slug": "royal-anne-hotel-kelowna", "user": {"distance": {"mi": 0, "km": 0}}}, {"city": {"url": "/", "name": "", "slug": ""}, "name": "Chez Nicole Bed and Breakfast", "img": "http://aff.bstatic.com/images/hotel/max500/119/11977158.jpg", "price_per_day_in_usd": 112, "url": "http://www.booking.com/hotel/ca/chez-nicole-bed-and-breakfast.html", "country": {"url": "/countries/", "name": "", "slug": ""}, "price": {"USD": 112, "CAD": 150}, "location": {"latitude": 49.901092727868, "longitude": -119.54947292805}, "distance_from_center_in_km": 4.098875873523, "type": "hotel", "slug": "chez-nicole-bed-and-breakfast-west-kelowna", "user": {"distance": {"mi": 2.4, "km": 4}}}, {"city": {"url": "/", "name": "", "slug": ""}, "name": "Wine Stopper B&B", "img": "http://aff.bstatic.com/images/hotel/max500/348/34817959.jpg", "price_per_day_in_usd": 112, "url": "http://www.booking.com/hotel/ca/wine-stopper-b-amp-b.html", "country": {"url": "/countries/", "name": "", "slug": ""}, "price": {"USD": 112, "CAD": 150}, "location": {"latitude": 49.759449052098, "longitude": -119.76140767336}, "distance_from_center_in_km": 23.804217616635, "type": "hotel", "slug": "wine-stopper-bb-peachland", "user": {"distance": {"mi": 13.8, "km": 23}}}, {"city": {"url": "/", "name": "", "slug": ""}, "name": "Myra Canyon Ranch B&B", "img": "http://aff.bstatic.com/images/hotel/max500/313/31364941.jpg", "price_per_day_in_usd": 116, "url": "http://www.booking.com/hotel/ca/myra-canyon-ranch-b-amp-b.html", "country": {"url": "/countries/", "name": "", "slug": ""}, "price": {"USD": 116, "CAD": 155}, "location": {"latitude": 49.810026208983, "longitude": -119.37809586525}, "distance_from_center_in_km": 12.106091062068, "type": "hotel", "slug": "myra-canyon-ranch-bb-kelowna", "user": {"distance": {"mi": 7.2, "km": 12}}}, {"city": {"url": "/", "name": "", "slug": ""}, "name": "Four Points by Sheraton Kelowna Airport", "img": "http://aff.bstatic.com/images/hotel/max500/200/20020110.jpg", "price_per_day_in_usd": 119, "url": "http://www.booking.com/hotel/ca/four-points-by-sheraton-kelowna-airport.html", "country": {"url": "/countries/", "name": "", "slug": ""}, "price": {"USD": 119, "CAD": 159}, "location": {"latitude": 49.951117810345, "longitude": -119.38344405206}, "distance_from_center_in_km": 10.690282629276, "type": "hotel", "slug": "four-points-by-sheraton-kelowna-airport-kelowna", "user": {"distance": {"mi": 6, "km": 10}}}, {"city": {"url": "/", "name": "", "slug": ""}, "name": "Fairfield Inn & Suites Kelowna", "img": "http://aff.bstatic.com/images/hotel/max500/334/33416042.jpg", "price_per_day_in_usd": 119, "url": "http://www.booking.com/hotel/ca/fairfield-inn-and-suites-by-marriott-kelowna.html", "country": {"url": "/countries/", "name": "", "slug": ""}, "price": {"USD": 119, "CAD": 159}, "location": {"latitude": 49.888824959472, "longitude": -119.42274928093}, "distance_from_center_in_km": 5.2493762175062, "type": "hotel", "slug": "fairfield-inn-suites-kelowna-kelowna", "user": {"distance": {"mi": 3, "km": 5}}}, {"city": {"url": "/", "name": "", "slug": ""}, "name": "Best Western PLUS Wine Country Hotel & Suites", "img": "http://aff.bstatic.com/images/hotel/max500/396/39631996.jpg", "price_per_day_in_usd": 120, "url": "http://www.booking.com/hotel/ca/best-western-wine-country.html", "country": {"url": "/countries/", "name": "", "slug": ""}, "price": {"USD": 120, "CAD": 160}, "location": {"latitude": 49.839099951665, "longitude": -119.60925936699}, "distance_from_center_in_km": 9.7672610089214, "type": "hotel", "slug": "best-western-plus-wine-country-hotel-suites-west-kelowna", "user": {"distance": {"mi": 5.4, "km": 9}}}, {"city": {"url": "/", "name": "", "slug": ""}, "name": "A Day's Dream B&B", "img": "http://aff.bstatic.com/images/hotel/max500/814/8147949.jpg", "price_per_day_in_usd": 120, "url": "http://www.booking.com/hotel/ca/a-day-s-dream-b.html", "country": {"url": "/countries/", "name": "", "slug": ""}, "price": {"USD": 120, "CAD": 160}, "location": {"latitude": 49.763284236136, "longitude": -119.75793153048}, "distance_from_center_in_km": 23.348975704137, "type": "hotel", "slug": "a-days-dream-bb-peachland", "user": {"distance": {"mi": 13.8, "km": 23}}}, {"city": {"url": "/", "name": "", "slug": ""}, "name": "A Touch of English B&B", "img": "http://aff.bstatic.com/images/hotel/max500/288/28827652.jpg", "price_per_day_in_usd": 123, "url": "http://www.booking.com/hotel/ca/a-touch-of-english-b-b.html", "country": {"url": "/countries/", "name": "", "slug": ""}, "price": {"USD": 123, "CAD": 165}, "location": {"latitude": 49.905450490527, "longitude": -119.4613020122}, "distance_from_center_in_km": 3.1570108212666, "type": "hotel", "slug": "a-touch-of-english-bb-kelowna", "user": {"distance": {"mi": 1.8, "km": 3}}}, {"city": {"url": "/", "name": "", "slug": ""}, "name": "Coast Capri Hotel", "img": "http://aff.bstatic.com/images/hotel/max500/315/31599984.jpg", "price_per_day_in_usd": 123, "url": "http://www.booking.com/hotel/ca/coast-capri.html", "country": {"url": "/countries/", "name": "", "slug": ""}, "price": {"USD": 123, "CAD": 165}, "location": {"latitude": 49.883114200026, "longitude": -119.47460308671}, "distance_from_center_in_km": 1.6253345331137, "type": "hotel", "slug": "coast-capri-hotel-kelowna", "user": {"distance": {"mi": 0.6, "km": 1}}}, {"city": {"url": "/", "name": "", "slug": ""}, "name": "Accent Inns Kelowna", "img": "http://aff.bstatic.com/images/hotel/max500/395/39521559.jpg", "price_per_day_in_usd": 126, "url": "http://www.booking.com/hotel/ca/accent-inn-kelowna.html", "country": {"url": "/countries/", "name": "", "slug": ""}, "price": {"USD": 126, "CAD": 169}, "location": {"latitude": 49.883906609346, "longitude": -119.47566658258}, "distance_from_center_in_km": 1.5253617205272, "type": "hotel", "slug": "accent-inns-kelowna-kelowna", "user": {"distance": {"mi": 0.6, "km": 1}}}, {"city": {"url": "/", "name": "", "slug": ""}, "name": "Hotel Zed Kelowna", "img": "http://aff.bstatic.com/images/hotel/max500/696/69654941.jpg", "price_per_day_in_usd": 126, "url": "http://www.booking.com/hotel/ca/kelowna-on-the-lake.html", "country": {"url": "/countries/", "name": "", "slug": ""}, "price": {"USD": 126, "CAD": 169}, "location": {"latitude": 49.884702462104, "longitude": -119.49925795197}, "distance_from_center_in_km": 0.42974385372416, "type": "hotel", "slug": "hotel-zed-kelowna-kelowna", "user": {"distance": {"mi": 0, "km": 0}}}, {"city": {"url": "/", "name": "", "slug": ""}, "name": "Prestige Beach House", "img": "http://aff.bstatic.com/images/hotel/max500/562/56250058.jpg", "price_per_day_in_usd": 127, "url": "http://www.booking.com/hotel/ca/the-prestige-kelowna.html", "country": {"url": "/countries/", "name": "", "slug": ""}, "price": {"USD": 127, "CAD": 170}, "location": {"latitude": 49.883908337597, "longitude": -119.4992646575}, "distance_from_center_in_km": 0.50647109790949, "type": "hotel", "slug": "prestige-beach-house-kelowna", "user": {"distance": {"mi": 0, "km": 0}}}, {"city": {"url": "/", "name": "", "slug": ""}, "name": "Best Western Plus Kelowna Hotel & Suites", "img": "http://aff.bstatic.com/images/hotel/max500/786/7866055.jpg", "price_per_day_in_usd": 135, "url": "http://www.booking.com/hotel/ca/best-western-kelowna.html", "country": {"url": "/countries/", "name": "", "slug": ""}, "price": {"USD": 135, "CAD": 180}, "location": {"latitude": 49.884938363821, "longitude": -119.4290176034}, "distance_from_center_in_km": 4.8112890066741, "type": "hotel", "slug": "best-western-plus-kelowna-hotel-suites-kelowna", "user": {"distance": {"mi": 2.4, "km": 4}}}, {"city": {"url": "/", "name": "", "slug": ""}, "name": "A Okanagan Lakeview B&B", "img": "http://aff.bstatic.com/images/hotel/max500/276/27696167.jpg", "price_per_day_in_usd": 135, "url": "http://www.booking.com/hotel/ca/a-okanagan-lakeview-b-amp-b.html", "country": {"url": "/countries/", "name": "", "slug": ""}, "price": {"USD": 135, "CAD": 180}, "location": {"latitude": 49.7956342, "longitude": -119.5049631}, "distance_from_center_in_km": 10.28531472934, "type": "hotel", "slug": "a-okanagan-lakeview-bb-kelowna", "user": {"distance": {"mi": 6, "km": 10}}}, {"city": {"url": "/", "name": "", "slug": ""}, "name": "Playa Del Sol Resort - Vacation Rentals", "img": "http://aff.bstatic.com/images/hotel/max500/387/3877017.jpg", "price_per_day_in_usd": 148, "url": "http://www.booking.com/hotel/ca/playa-del-sol-resort.html", "country": {"url": "/countries/", "name": "", "slug": ""}, "price": {"USD": 148, "CAD": 198}, "location": {"latitude": 49.845833804216, "longitude": -119.48615133762}, "distance_from_center_in_km": 4.736328617982, "type": "hotel", "slug": "playa-del-sol-resort-vacation-rentals-kelowna", "user": {"distance": {"mi": 2.4, "km": 4}}}, {"city": {"url": "/", "name": "", "slug": ""}, "name": "The Cove Lakeside Resort", "img": "http://aff.bstatic.com/images/hotel/max500/503/5034105.jpg", "price_per_day_in_usd": 156, "url": "http://www.booking.com/hotel/ca/the-cove-lakeside-resort.html", "country": {"url": "/countries/", "name": "", "slug": ""}, "price": {"USD": 156, "CAD": 209}, "location": {"latitude": 49.811237819552, "longitude": -119.62418049574}, "distance_from_center_in_km": 12.538423565822, "type": "hotel", "slug": "the-cove-lakeside-resort-west-kelowna", "user": {"distance": {"mi": 7.2, "km": 12}}}, {"city": {"url": "/", "name": "", "slug": ""}, "name": "Acker Vacation Rentals Kelowna", "img": "http://aff.bstatic.com/images/hotel/max500/456/45648740.jpg", "price_per_day_in_usd": 169, "url": "http://www.booking.com/hotel/ca/acker-vacation-rentals-kelowna.html", "country": {"url": "/countries/", "name": "", "slug": ""}, "price": {"USD": 169, "CAD": 226}, "location": {"latitude": 49.877827969964, "longitude": -119.36614394188}, "distance_from_center_in_km": 9.3726232520109, "type": "hotel", "slug": "acker-vacation-rentals-kelowna-kelowna", "user": {"distance": {"mi": 5.4, "km": 9}}}, {"city": {"url": "/", "name": "", "slug": ""}, "name": "Delta Hotels by Marriott Grand Okanagan Resort", "img": "http://aff.bstatic.com/images/hotel/max500/880/8809297.jpg", "price_per_day_in_usd": 171, "url": "http://www.booking.com/hotel/ca/delta-grand-okanagan-resort.html", "country": {"url": "/countries/", "name": "", "slug": ""}, "price": {"USD": 171, "CAD": 229}, "location": {"latitude": 49.89154832779, "longitude": -119.49757754803}, "distance_from_center_in_km": 0.41536073910643, "type": "hotel", "slug": "delta-hotels-by-marriott-grand-okanagan-resort-kelowna", "user": {"distance": {"mi": 0, "km": 0}}}, {"city": {"url": "/", "name": "", "slug": ""}, "name": "Hotel Eldorado", "img": "http://aff.bstatic.com/images/hotel/max500/321/32120755.jpg", "price_per_day_in_usd": 208, "url": "http://www.booking.com/hotel/ca/eldorado.html", "country": {"url": "/countries/", "name": "", "slug": ""}, "price": {"USD": 208, "CAD": 279}, "location": {"latitude": 49.845769808491, "longitude": -119.48898643255}, "distance_from_center_in_km": 4.7173750766714, "type": "hotel", "slug": "hotel-eldorado-kelowna", "user": {"distance": {"mi": 2.4, "km": 4}}}, {"city": {"url": "/", "name": "", "slug": ""}, "name": "A Loft with a View", "img": "http://aff.bstatic.com/images/hotel/max500/593/5930305.jpg", "price_per_day_in_usd": 224, "url": "http://www.booking.com/hotel/ca/a-loft-with-a-view.html", "country": {"url": "/countries/", "name": "", "slug": ""}, "price": {"USD": 224, "CAD": 300}, "location": {"latitude": 49.840333321817, "longitude": -119.43403869867}, "distance_from_center_in_km": 6.9113789525341, "type": "hotel", "slug": "a-loft-with-a-view-kelowna", "user": {"distance": {"mi": 3.6, "km": 6}}}, {"city": {"url": "/", "name": "", "slug": ""}, "name": "Beach Ave Castle Luxury Vacation Rental", "img": "http://aff.bstatic.com/images/hotel/max500/103/10300797.jpg", "price_per_day_in_usd": 523, "url": "http://www.booking.com/hotel/ca/beach-ave-castle-luxury-vacation-rental.html", "country": {"url": "/countries/", "name": "", "slug": ""}, "price": {"USD": 523, "CAD": 700}, "location": {"latitude": 49.787209382472, "longitude": -119.70803171396}, "distance_from_center_in_km": 18.886140311645, "type": "hotel", "slug": "beach-ave-castle-luxury-vacation-rental-peachland", "user": {"distance": {"mi": 10.8, "km": 18}}}, {"city": {"url": "/", "name": "", "slug": ""}, "name": "Lakeshore B&B", "img": "http://aff.bstatic.com/images/hotel/max500/709/70964156.jpg", "price_per_day_in_usd": 0, "url": "http://www.booking.com/hotel/ca/lakeshore-b-b.html", "country": {"url": "/countries/", "name": "", "slug": ""}, "location": {"latitude": 49.832818, "longitude": -119.486957}, "distance_from_center_in_km": 6.1648645129688, "type": "hotel", "slug": "lakeshore-bb-kelowna"}, {"city": {"url": "/", "name": "", "slug": ""}, "name": "Quails Quest Bed & Breakfast", "img": "http://aff.bstatic.com/images/hotel/max500/103/10304455.jpg", "price_per_day_in_usd": 0, "url": "http://www.booking.com/hotel/ca/quails-quest-bed.html", "country": {"url": "/countries/", "name": "", "slug": ""}, "location": {"latitude": 49.845874450106, "longitude": -119.57107409835}, "distance_from_center_in_km": 7.1298902384084, "type": "hotel", "slug": "quails-quest-bed-breakfast-west-kelowna"}]