[{"city": {"url": "/wroclaw-poland", "name": "Wroc\u0142aw", "slug": "wroclaw-poland"}, "name": "Bemma", "img": "http://ucd.hwstatic.com/propertyimages/5/58005/7.jpg", "price_per_day_in_usd": 21, "url": "http://www.hostelworld.com/hosteldetails.php/Bemma/Wroclaw/58005", "country": {"url": "/countries/poland", "name": "Poland", "slug": "poland"}, "price": {"PLN": 85, "USD": 21}, "location": {"latitude": 51.1099484, "longitude": 17.0262229}, "distance_from_center_in_km": 0.88980781575298, "type": "hotel", "slug": "bemma-ul-kazimierza-wielkiego-15-wroclaw-wroclaw", "user": {"distance": {"mi": 0, "km": 0}}}, {"city": {"url": "/", "name": "", "slug": ""}, "name": "Hotel Wieniawa", "img": "http://aff.bstatic.com/images/hotel/max500/344/34491993.jpg", "price_per_day_in_usd": 22, "url": "http://www.booking.com/hotel/pl/wieniawawroclaw.html", "country": {"url": "/countries/", "name": "", "slug": ""}, "price": {"PLN": 88, "USD": 22}, "location": {"latitude": 51.090027005929, "longitude": 17.007664740086}, "distance_from_center_in_km": 2.9309692181825, "type": "hotel", "slug": "hotel-wieniawa-wroclaw", "user": {"distance": {"mi": 1.2, "km": 2}}}, {"city": {"url": "/wroclaw-poland", "name": "Wroc\u0142aw", "slug": "wroclaw-poland"}, "name": "Big City Hostel", "img": "http://ucd.hwstatic.com/propertyimages/2/264807/501.jpg", "price_per_day_in_usd": 23, "url": "http://www.hostelworld.com/hosteldetails.php/Big-City-Hostel/Wroclaw/264807", "country": {"url": "/countries/poland", "name": "Poland", "slug": "poland"}, "price": {"PLN": 90, "USD": 23}, "location": {"latitude": 51.1051387, "longitude": 17.0128297}, "distance_from_center_in_km": 1.8206315679313, "type": "hotel", "slug": "big-city-hostel-teczowa-57-wroclaw-wroclaw", "user": {"distance": {"mi": 0.6, "km": 1}}}, {"city": {"url": "/wroclaw-poland", "name": "Wroc\u0142aw", "slug": "wroclaw-poland"}, "name": "Boogie Hostel", "img": "http://ucd.hwstatic.com/propertyimages/2/25038/12.jpg", "price_per_day_in_usd": 25, "url": "http://www.hostelworld.com/hosteldetails.php/Boogie-Hostel/Wroclaw/25038", "country": {"url": "/countries/poland", "name": "Poland", "slug": "poland"}, "price": {"PLN": 99, "USD": 25}, "location": {"latitude": 51.1109183, "longitude": 17.024281}, "distance_from_center_in_km": 1.0508742393871, "type": "hotel", "slug": "boogie-hostel-ruska-34-street-wroclaw-wroclaw", "user": {"distance": {"mi": 0.6, "km": 1}}}, {"city": {"url": "/wroclaw-poland", "name": "Wroc\u0142aw", "slug": "wroclaw-poland"}, "name": "Green Hostel Wroclaw", "img": "http://ucd.hwstatic.com/propertyimages/5/54448/1.jpg", "price_per_day_in_usd": 25, "url": "http://www.hostelworld.com/hosteldetails.php/Green-Hostel-Wroclaw/Wroclaw/54448", "country": {"url": "/countries/poland", "name": "Poland", "slug": "poland"}, "price": {"PLN": 100, "USD": 25}, "location": {"latitude": 51.1082105, "longitude": 17.0705866}, "distance_from_center_in_km": 2.2377660501031, "type": "hotel", "slug": "green-hostel-wroclaw-mickiewicza-4-wroclaw-wroclaw", "user": {"distance": {"mi": 1.2, "km": 2}}}, {"city": {"url": "/wroclaw-poland", "name": "Wroc\u0142aw", "slug": "wroclaw-poland"}, "name": "Absynt Hostel", "img": "http://ucd.hwstatic.com/propertyimages/5/53892/1.jpg", "price_per_day_in_usd": 26, "url": "http://www.hostelworld.com/hosteldetails.php/Absynt-Hostel/Wroclaw/53892", "country": {"url": "/countries/poland", "name": "Poland", "slug": "poland"}, "price": {"PLN": 105, "USD": 26}, "location": {"latitude": 51.1092343, "longitude": 17.0256328}, "distance_from_center_in_km": 0.91333158583958, "type": "hotel", "slug": "absynt-hostel-antoniego-15-wroclaw-wroclaw", "user": {"distance": {"mi": 0, "km": 0}}}, {"city": {"url": "/", "name": "", "slug": ""}, "name": "Quality System - Hotel Wroc\u0142aw", "img": "http://aff.bstatic.com/images/hotel/max500/388/388215.jpg", "price_per_day_in_usd": 27, "url": "http://www.booking.com/hotel/pl/hspremiumwroclaw.html", "country": {"url": "/countries/", "name": "", "slug": ""}, "price": {"PLN": 109, "USD": 27}, "location": {"latitude": 51.131656355762, "longitude": 17.061531543732}, "distance_from_center_in_km": 3.0923072515153, "type": "hotel", "slug": "quality-system-hotel-wroclaw-wroclaw", "user": {"distance": {"mi": 1.8, "km": 3}}}, {"city": {"url": "/wroclaw-poland", "name": "Wroc\u0142aw", "slug": "wroclaw-poland"}, "name": "Moon Hostel", "img": "http://ucd.hwstatic.com/propertyimages/3/36175/1.jpg", "price_per_day_in_usd": 30, "url": "http://www.hostelworld.com/hosteldetails.php/Moon-Hostel/Wroclaw/36175", "country": {"url": "/countries/poland", "name": "Poland", "slug": "poland"}, "price": {"PLN": 120, "USD": 30}, "location": {"latitude": 51.1083014, "longitude": 17.0274943}, "distance_from_center_in_km": 0.77236559878704, "type": "hotel", "slug": "moon-hostel-6-8-krupnicza-street-entrance-from-kazimierza-wielkiego-27-wroclaw-wroclaw", "user": {"distance": {"mi": 0, "km": 0}}}, {"city": {"url": "/wroclaw-poland", "name": "Wroc\u0142aw", "slug": "wroclaw-poland"}, "name": "Piaskowy Hostel", "img": "http://ucd.hwstatic.com/propertyimages/7/79180/9.jpg", "price_per_day_in_usd": 30, "url": "http://www.hostelworld.com/hosteldetails.php/Piaskowy-Hostel/Wroclaw/79180", "country": {"url": "/countries/poland", "name": "Poland", "slug": "poland"}, "price": {"PLN": 120, "USD": 30}, "location": {"latitude": 51.112527, "longitude": 17.0394766}, "distance_from_center_in_km": 0.52029066826103, "type": "hotel", "slug": "piaskowy-hostel-piaskowa-15-wroclaw-wroclaw", "user": {"distance": {"mi": 0, "km": 0}}}, {"city": {"url": "/", "name": "", "slug": ""}, "name": "Platinium Centrum", "img": "http://aff.bstatic.com/images/hotel/max500/108/1081360.jpg", "price_per_day_in_usd": 33, "url": "http://www.booking.com/hotel/pl/platiniumwroclaw.html", "country": {"url": "/countries/", "name": "", "slug": ""}, "price": {"PLN": 130, "USD": 33}, "location": {"latitude": 51.102996469062, "longitude": 17.042654156685}, "distance_from_center_in_km": 0.61490470389383, "type": "hotel", "slug": "platinium-centrum-wroclaw", "user": {"distance": {"mi": 0, "km": 0}}}, {"city": {"url": "/wroclaw-poland", "name": "Wroc\u0142aw", "slug": "wroclaw-poland"}, "name": "The One", "img": "http://ucd.hwstatic.com/propertyimages/5/55142/7.jpg", "price_per_day_in_usd": 33, "url": "http://www.hostelworld.com/hosteldetails.php/The-One/Wroclaw/55142", "country": {"url": "/countries/poland", "name": "Poland", "slug": "poland"}, "price": {"PLN": 130, "USD": 33}, "location": {"latitude": 51.1093893, "longitude": 17.0330572}, "distance_from_center_in_km": 0.41756228608189, "type": "hotel", "slug": "the-one-rynek-30-wroclaw-wroclaw", "user": {"distance": {"mi": 0, "km": 0}}}, {"city": {"url": "/wroclaw-poland", "name": "Wroc\u0142aw", "slug": "wroclaw-poland"}, "name": "Friends Hostel & Apartments", "img": "http://ucd.hwstatic.com/propertyimages/5/55323/501.jpg", "price_per_day_in_usd": 34, "url": "http://www.hostelworld.com/hosteldetails.php/Friends-Hostel-and-Apartments/Wroclaw/55323", "country": {"url": "/countries/poland", "name": "Poland", "slug": "poland"}, "price": {"PLN": 136, "USD": 34}, "location": {"latitude": 51.1105546, "longitude": 17.0253646}, "distance_from_center_in_km": 0.96635359145182, "type": "hotel", "slug": "friends-hostel-apartments-ul-ruska-49-wroclaw-wroclaw", "user": {"distance": {"mi": 0, "km": 0}}}, {"city": {"url": "/wroclaw-poland", "name": "Wroc\u0142aw", "slug": "wroclaw-poland"}, "name": "Cinnamon Hostel", "img": "http://ucd.hwstatic.com/propertyimages/1/19656/53.jpg", "price_per_day_in_usd": 38, "url": "http://www.hostelworld.com/hosteldetails.php/Cinnamon-Hostel/Wroclaw/19656", "country": {"url": "/countries/poland", "name": "Poland", "slug": "poland"}, "price": {"PLN": 150, "USD": 38}, "location": {"latitude": 51.106971, "longitude": 17.0347738}, "distance_from_center_in_km": 0.28174758596077, "type": "hotel", "slug": "cinnamon-hostel-str-kazimierza-wielkiego-67-wroclaw-wroclaw", "user": {"distance": {"mi": 0, "km": 0}}}, {"city": {"url": "/wroclaw-poland", "name": "Wroc\u0142aw", "slug": "wroclaw-poland"}, "name": "Hostel Wratislavia", "img": "http://ucd.hwstatic.com/propertyimages/6/61410/5.jpg", "price_per_day_in_usd": 38, "url": "http://www.hostelworld.com/hosteldetails.php/Hostel-Wratislavia/Wroclaw/61410", "country": {"url": "/countries/poland", "name": "Poland", "slug": "poland"}, "price": {"PLN": 152, "USD": 38}, "location": {"latitude": 51.1030368, "longitude": 17.043035}, "distance_from_center_in_km": 0.62389381452426, "type": "hotel", "slug": "hostel-wratislavia-komuny-paryskiej-19-wroclaw-wroclaw", "user": {"distance": {"mi": 0, "km": 0}}}, {"city": {"url": "/", "name": "", "slug": ""}, "name": "Campanile Wroclaw - Stare Miasto", "img": "http://aff.bstatic.com/images/hotel/max500/119/11962325.jpg", "price_per_day_in_usd": 39, "url": "http://www.booking.com/hotel/pl/wroclawwroc.html", "country": {"url": "/countries/", "name": "", "slug": ""}, "price": {"PLN": 153, "USD": 39}, "location": {"latitude": 51.116741020716, "longitude": 17.026067376137}, "distance_from_center_in_km": 1.3143360301372, "type": "hotel", "slug": "campanile-wroclaw-stare-miasto-wroclaw", "user": {"distance": {"mi": 0.6, "km": 1}}}, {"city": {"url": "/", "name": "", "slug": ""}, "name": "Akira Bed&Breakfast", "img": "http://aff.bstatic.com/images/hotel/max500/194/19447781.jpg", "price_per_day_in_usd": 40, "url": "http://www.booking.com/hotel/pl/hotelakirabedbreakfastwroclaw.html", "country": {"url": "/countries/", "name": "", "slug": ""}, "price": {"PLN": 159, "USD": 40}, "location": {"latitude": 51.121854610792, "longitude": 17.027220055461}, "distance_from_center_in_km": 1.7426816914218, "type": "hotel", "slug": "akira-bedbreakfast-wroclaw", "user": {"distance": {"mi": 0.6, "km": 1}}}, {"city": {"url": "/wroclaw-poland", "name": "Wroc\u0142aw", "slug": "wroclaw-poland"}, "name": "Akira Bed & Breakfast", "img": "http://ucd.hwstatic.com/propertyimages/3/32785/3.jpg", "price_per_day_in_usd": 40, "url": "http://www.hostelworld.com/hosteldetails.php/Akira-Bed-and-Breakfast/Wroclaw/32785", "country": {"url": "/countries/poland", "name": "Poland", "slug": "poland"}, "price": {"PLN": 159, "USD": 40}, "location": {"latitude": 51.1218962, "longitude": 17.0273709}, "distance_from_center_in_km": 1.7420680573246, "type": "hotel", "slug": "akira-bed-breakfast-plac-strzelecki-28-wroc322aw-wroclaw-wroclaw", "user": {"distance": {"mi": 0.6, "km": 1}}}, {"city": {"url": "/", "name": "", "slug": ""}, "name": "Karczma Rzym", "img": "http://aff.bstatic.com/images/hotel/max500/143/14305843.jpg", "price_per_day_in_usd": 40, "url": "http://www.booking.com/hotel/pl/karczmarzymwroclaw.html", "country": {"url": "/countries/", "name": "", "slug": ""}, "price": {"PLN": 160, "USD": 40}, "location": {"latitude": 51.121434988575, "longitude": 16.84424713254}, "distance_from_center_in_km": 13.645712268316, "type": "hotel", "slug": "karczma-rzym-wroclaw", "user": {"distance": {"mi": 7.8, "km": 13}}}, {"city": {"url": "/wroclaw-poland", "name": "Wroc\u0142aw", "slug": "wroclaw-poland"}, "name": "Royal Hostel", "img": "http://ucd.hwstatic.com/propertyimages/3/37078/2.jpg", "price_per_day_in_usd": 40, "url": "http://www.hostelworld.com/hosteldetails.php/Royal-Hostel/Wroclaw/37078", "country": {"url": "/countries/poland", "name": "Poland", "slug": "poland"}, "price": {"PLN": 160, "USD": 40}, "location": {"latitude": 51.1080488, "longitude": 17.0275211}, "distance_from_center_in_km": 0.76932404092814, "type": "hotel", "slug": "royal-hostel-kazimierza-wielkiego-27-wroc322aw-wroclaw-wroclaw", "user": {"distance": {"mi": 0, "km": 0}}}, {"city": {"url": "/", "name": "", "slug": ""}, "name": "Jasek Premium Hotel Wroc\u0142aw", "img": "http://aff.bstatic.com/images/hotel/max500/333/33377600.jpg", "price_per_day_in_usd": 41, "url": "http://www.booking.com/hotel/pl/jasekwroclaw.html", "country": {"url": "/countries/", "name": "", "slug": ""}, "price": {"PLN": 161, "USD": 41}, "location": {"latitude": 51.174910921533, "longitude": 17.023010328412}, "distance_from_center_in_km": 7.5312302715607, "type": "hotel", "slug": "jasek-premium-hotel-wroclaw-wroclaw", "user": {"distance": {"mi": 4.2, "km": 7}}}, {"city": {"url": "/wroclaw-poland", "name": "Wroc\u0142aw", "slug": "wroclaw-poland"}, "name": "Boogie Deluxe", "img": "http://ucd.hwstatic.com/propertyimages/4/40666/9.jpg", "price_per_day_in_usd": 41, "url": "http://www.hostelworld.com/hosteldetails.php/Boogie-Deluxe/Wroclaw/40666", "country": {"url": "/countries/poland", "name": "Poland", "slug": "poland"}, "price": {"PLN": 164, "USD": 41}, "location": {"latitude": 51.1111406, "longitude": 17.027328}, "distance_from_center_in_km": 0.86222887615545, "type": "hotel", "slug": "boogie-deluxe-ulbialoskornicza-6-wroclaw-wroclaw", "user": {"distance": {"mi": 0, "km": 0}}}, {"city": {"url": "/", "name": "", "slug": ""}, "name": "Novotel Wroc\u0142aw City", "img": "http://aff.bstatic.com/images/hotel/max500/141/14165080.jpg", "price_per_day_in_usd": 42, "url": "http://www.booking.com/hotel/pl/wroclaw.html", "country": {"url": "/countries/", "name": "", "slug": ""}, "price": {"PLN": 165, "USD": 42}, "location": {"latitude": 51.068504277925, "longitude": 17.008407711983}, "distance_from_center_in_km": 4.8583701965985, "type": "hotel", "slug": "novotel-wroclaw-city-wroclaw", "user": {"distance": {"mi": 2.4, "km": 4}}}, {"city": {"url": "/", "name": "", "slug": ""}, "name": "Hotel Europejski Wroc\u0142aw Centrum", "img": "http://aff.bstatic.com/images/hotel/max500/625/62546288.jpg", "price_per_day_in_usd": 43, "url": "http://www.booking.com/hotel/pl/silfor-premium-europejski-wroclaw.html", "country": {"url": "/countries/", "name": "", "slug": ""}, "price": {"PLN": 171, "USD": 43}, "location": {"latitude": 51.100383582072, "longitude": 17.034283317626}, "distance_from_center_in_km": 0.88545015893631, "type": "hotel", "slug": "hotel-europejski-wroclaw-centrum-wroclaw", "user": {"distance": {"mi": 0, "km": 0}}}, {"city": {"url": "/", "name": "", "slug": ""}, "name": "Hotel Tumski", "img": "http://aff.bstatic.com/images/hotel/max500/516/51642222.jpg", "price_per_day_in_usd": 45, "url": "http://www.booking.com/hotel/pl/integertumskiwroclaw.html", "country": {"url": "/countries/", "name": "", "slug": ""}, "price": {"PLN": 179, "USD": 45}, "location": {"latitude": 51.115974922588, "longitude": 17.040548622608}, "distance_from_center_in_km": 0.91042487514262, "type": "hotel", "slug": "hotel-tumski-wroclaw", "user": {"distance": {"mi": 0, "km": 0}}}, {"city": {"url": "/", "name": "", "slug": ""}, "name": "Park Hotel Diament Wroclaw", "img": "http://aff.bstatic.com/images/hotel/max500/336/33697253.jpg", "price_per_day_in_usd": 47, "url": "http://www.booking.com/hotel/pl/diamentwroclaw.html", "country": {"url": "/countries/", "name": "", "slug": ""}, "price": {"PLN": 187, "USD": 47}, "location": {"latitude": 51.109625079753, "longitude": 16.971918940544}, "distance_from_center_in_km": 4.6548759222457, "type": "hotel", "slug": "park-hotel-diament-wroclaw-wroclaw", "user": {"distance": {"mi": 2.4, "km": 4}}}, {"city": {"url": "/", "name": "", "slug": ""}, "name": "Business Hotel Vega Wroc\u0142aw", "img": "http://aff.bstatic.com/images/hotel/max500/495/49576676.jpg", "price_per_day_in_usd": 48, "url": "http://www.booking.com/hotel/pl/vegawroclaw.html", "country": {"url": "/countries/", "name": "", "slug": ""}, "price": {"PLN": 189, "USD": 48}, "location": {"latitude": 51.096316373894, "longitude": 16.985281705856}, "distance_from_center_in_km": 3.9347177430558, "type": "hotel", "slug": "business-hotel-vega-wroclaw-wroclaw", "user": {"distance": {"mi": 1.8, "km": 3}}}, {"city": {"url": "/", "name": "", "slug": ""}, "name": "Academus - Cafe/Pub & Guest House", "img": "http://aff.bstatic.com/images/hotel/max500/323/32391482.jpg", "price_per_day_in_usd": 48, "url": "http://www.booking.com/hotel/pl/academus-pub-apartments-wroclaw.html", "country": {"url": "/countries/", "name": "", "slug": ""}, "price": {"PLN": 189, "USD": 48}, "location": {"latitude": 51.111909338762, "longitude": 17.02981710434}, "distance_from_center_in_km": 0.75554528780091, "type": "hotel", "slug": "academus-cafe-pub-guest-house-wroclaw", "user": {"distance": {"mi": 0, "km": 0}}}, {"city": {"url": "/", "name": "", "slug": ""}, "name": "AS Apartments/Market Square", "img": "http://aff.bstatic.com/images/hotel/max500/375/37514680.jpg", "price_per_day_in_usd": 48, "url": "http://www.booking.com/hotel/pl/apartamentrynekratuszwroclaw.html", "country": {"url": "/countries/", "name": "", "slug": ""}, "price": {"PLN": 190, "USD": 48}, "location": {"latitude": 51.109348233035, "longitude": 17.031087130308}, "distance_from_center_in_km": 0.54498888623587, "type": "hotel", "slug": "as-apartments-market-square-wroclaw", "user": {"distance": {"mi": 0, "km": 0}}}, {"city": {"url": "/", "name": "", "slug": ""}, "name": "Pensjonat Rezydencja Parkowa", "img": "http://aff.bstatic.com/images/hotel/max500/683/6836366.jpg", "price_per_day_in_usd": 49, "url": "http://www.booking.com/hotel/pl/rezydencjaparkowawroclaw.html", "country": {"url": "/countries/", "name": "", "slug": ""}, "price": {"PLN": 195, "USD": 49}, "location": {"latitude": 51.087162099326, "longitude": 16.985386312008}, "distance_from_center_in_km": 4.3686918540134, "type": "hotel", "slug": "pensjonat-rezydencja-parkowa-wroclaw", "user": {"distance": {"mi": 2.4, "km": 4}}}, {"city": {"url": "/", "name": "", "slug": ""}, "name": "Premium Hotel Bacero Wroc\u0142aw", "img": "http://aff.bstatic.com/images/hotel/max500/213/21350050.jpg", "price_per_day_in_usd": 50, "url": "http://www.booking.com/hotel/pl/hotelbacerowroclaw.html", "country": {"url": "/countries/", "name": "", "slug": ""}, "price": {"PLN": 199, "USD": 50}, "location": {"latitude": 51.060153679711, "longitude": 17.007177919149}, "distance_from_center_in_km": 5.7417611272141, "type": "hotel", "slug": "premium-hotel-bacero-wroclaw-wroclaw", "user": {"distance": {"mi": 3, "km": 5}}}, {"city": {"url": "/", "name": "", "slug": ""}, "name": "HP Park Plaza", "img": "http://aff.bstatic.com/images/hotel/max500/140/14036205.jpg", "price_per_day_in_usd": 50, "url": "http://www.booking.com/hotel/pl/hpparkplazawroclaw.html", "country": {"url": "/countries/", "name": "", "slug": ""}, "price": {"PLN": 199, "USD": 50}, "location": {"latitude": 51.117414503084, "longitude": 17.03558921814}, "distance_from_center_in_km": 1.079414122941, "type": "hotel", "slug": "hp-park-plaza-wroclaw", "user": {"distance": {"mi": 0.6, "km": 1}}}, {"city": {"url": "/", "name": "", "slug": ""}, "name": "Hotel Patio", "img": "http://aff.bstatic.com/images/hotel/max500/495/49573014.jpg", "price_per_day_in_usd": 52, "url": "http://www.booking.com/hotel/pl/patiowroclaw.html", "country": {"url": "/countries/", "name": "", "slug": ""}, "price": {"PLN": 207, "USD": 52}, "location": {"latitude": 51.111810830844, "longitude": 17.029803693295}, "distance_from_center_in_km": 0.74987173577827, "type": "hotel", "slug": "hotel-patio-wroclaw", "user": {"distance": {"mi": 0, "km": 0}}}, {"city": {"url": "/", "name": "", "slug": ""}, "name": "Scandic Wroc\u0142aw", "img": "http://aff.bstatic.com/images/hotel/max500/511/51151262.jpg", "price_per_day_in_usd": 55, "url": "http://www.booking.com/hotel/pl/holidayinnwroclaw.html", "country": {"url": "/countries/", "name": "", "slug": ""}, "price": {"PLN": 219, "USD": 55}, "location": {"latitude": 51.101395591179, "longitude": 17.028148770332}, "distance_from_center_in_km": 1.0231532245656, "type": "hotel", "slug": "scandic-wroclaw-wroclaw", "user": {"distance": {"mi": 0.6, "km": 1}}}, {"city": {"url": "/wroclaw-poland", "name": "Wroc\u0142aw", "slug": "wroclaw-poland"}, "name": "Mleczarnia Hostel", "img": "http://ucd.hwstatic.com/propertyimages/2/21878/3.jpg", "price_per_day_in_usd": 55, "url": "http://www.hostelworld.com/hosteldetails.php/Mleczarnia-Hostel/Wroclaw/21878", "country": {"url": "/countries/poland", "name": "Poland", "slug": "poland"}, "price": {"PLN": 220, "USD": 55}, "location": {"latitude": 51.1081162, "longitude": 17.0250535}, "distance_from_center_in_km": 0.9417323062354, "type": "hotel", "slug": "mleczarnia-hostel-ul-wodkowica-5-wroclaw-wroclaw", "user": {"distance": {"mi": 0, "km": 0}}}, {"city": {"url": "/", "name": "", "slug": ""}, "name": "Hotel im. Jana Paw\u0142a II", "img": "http://aff.bstatic.com/images/hotel/max500/443/44353851.jpg", "price_per_day_in_usd": 61, "url": "http://www.booking.com/hotel/pl/pensjonatjanapawlaiiwroclaw.html", "country": {"url": "/countries/", "name": "", "slug": ""}, "price": {"PLN": 243, "USD": 61}, "location": {"latitude": 51.114904047655, "longitude": 17.044781148434}, "distance_from_center_in_km": 0.89391781424993, "type": "hotel", "slug": "hotel-im-jana-pawla-ii-wroclaw", "user": {"distance": {"mi": 0, "km": 0}}}, {"city": {"url": "/", "name": "", "slug": ""}, "name": "Europeum Hotel", "img": "http://aff.bstatic.com/images/hotel/max500/347/34743628.jpg", "price_per_day_in_usd": 62, "url": "http://www.booking.com/hotel/pl/europeumwroclaw.html", "country": {"url": "/countries/", "name": "", "slug": ""}, "price": {"PLN": 245, "USD": 62}, "location": {"latitude": 51.108133051616, "longitude": 17.027939558029}, "distance_from_center_in_km": 0.74040701674451, "type": "hotel", "slug": "europeum-hotel-wroclaw", "user": {"distance": {"mi": 0, "km": 0}}}, {"city": {"url": "/", "name": "", "slug": ""}, "name": "Radisson Blu Hotel", "img": "http://aff.bstatic.com/images/hotel/max500/645/64505069.jpg", "price_per_day_in_usd": 64, "url": "http://www.booking.com/hotel/pl/radissonsaswroclaw.html", "country": {"url": "/countries/", "name": "", "slug": ""}, "price": {"PLN": 256, "USD": 64}, "location": {"latitude": 51.11109601068, "longitude": 17.044282928109}, "distance_from_center_in_km": 0.53697560521689, "type": "hotel", "slug": "radisson-blu-hotel-wroclaw", "user": {"distance": {"mi": 0, "km": 0}}}, {"city": {"url": "/wroclaw-poland", "name": "Wroc\u0142aw", "slug": "wroclaw-poland"}, "name": "Chopper Hostel", "img": "http://ucd.hwstatic.com/propertyimages/5/54856/9.jpg", "price_per_day_in_usd": 65, "url": "http://www.hostelworld.com/hosteldetails.php/Chopper-Hostel/Wroclaw/54856", "country": {"url": "/countries/poland", "name": "Poland", "slug": "poland"}, "price": {"PLN": 260, "USD": 65}, "location": {"latitude": 51.1112551, "longitude": 17.0347738}, "distance_from_center_in_km": 0.45766101307504, "type": "hotel", "slug": "chopper-hostel-kotlarska-42-wroclaw-wroclaw", "user": {"distance": {"mi": 0, "km": 0}}}, {"city": {"url": "/", "name": "", "slug": ""}, "name": "Centrum Dikul Hotel", "img": "http://aff.bstatic.com/images/hotel/max500/341/34142886.jpg", "price_per_day_in_usd": 68, "url": "http://www.booking.com/hotel/pl/centrumdikulwroclaw.html", "country": {"url": "/countries/", "name": "", "slug": ""}, "price": {"PLN": 270, "USD": 68}, "location": {"latitude": 51.11267634623, "longitude": 17.026526033878}, "distance_from_center_in_km": 0.99346248098619, "type": "hotel", "slug": "centrum-dikul-hotel-wroclaw", "user": {"distance": {"mi": 0, "km": 0}}}, {"city": {"url": "/", "name": "", "slug": ""}, "name": "Mercure Wroc\u0142aw Centrum", "img": "http://aff.bstatic.com/images/hotel/max500/333/33376321.jpg", "price_per_day_in_usd": 74, "url": "http://www.booking.com/hotel/pl/panorama.html", "country": {"url": "/countries/", "name": "", "slug": ""}, "price": {"PLN": 293, "USD": 74}, "location": {"latitude": 51.108607946158, "longitude": 17.039022445679}, "distance_from_center_in_km": 0.087203197711973, "type": "hotel", "slug": "mercure-wroclaw-centrum-wroclaw", "user": {"distance": {"mi": 0, "km": 0}}}, {"city": {"url": "/", "name": "", "slug": ""}, "name": "Qubus Hotel Wroc\u0142aw", "img": "http://aff.bstatic.com/images/hotel/max500/329/32936845.jpg", "price_per_day_in_usd": 79, "url": "http://www.booking.com/hotel/pl/qubuswroclaw.html", "country": {"url": "/countries/", "name": "", "slug": ""}, "price": {"PLN": 313, "USD": 79}, "location": {"latitude": 51.109249551248, "longitude": 17.034762427211}, "distance_from_center_in_km": 0.30410223100451, "type": "hotel", "slug": "qubus-hotel-wroclaw-wroclaw", "user": {"distance": {"mi": 0, "km": 0}}}, {"city": {"url": "/", "name": "", "slug": ""}, "name": "Sofitel Wroclaw Old Town", "img": "http://aff.bstatic.com/images/hotel/max500/193/19301842.jpg", "price_per_day_in_usd": 80, "url": "http://www.booking.com/hotel/pl/wroclaww.html", "country": {"url": "/countries/", "name": "", "slug": ""}, "price": {"PLN": 317, "USD": 80}, "location": {"latitude": 51.111437845966, "longitude": 17.028331160545}, "distance_from_center_in_km": 0.81470927857345, "type": "hotel", "slug": "sofitel-wroclaw-old-town-wroclaw", "user": {"distance": {"mi": 0, "km": 0}}}, {"city": {"url": "/wroclaw-poland", "name": "Wroc\u0142aw", "slug": "wroclaw-poland"}, "name": "Gem Hotel", "img": "http://ucd.hwstatic.com/propertyimages/7/79919/1.jpg", "price_per_day_in_usd": 86, "url": "http://www.hostelworld.com/hosteldetails.php/Gem-Hotel/Wroclaw/79919", "country": {"url": "/countries/poland", "name": "Poland", "slug": "poland"}, "price": {"PLN": 341, "USD": 86}, "location": {"latitude": 51.123775, "longitude": 17.0719224}, "distance_from_center_in_km": 2.9244301856008, "type": "hotel", "slug": "gem-hotel-ul-mianowskiego-2b-wroclaw-wroclaw", "user": {"distance": {"mi": 1.2, "km": 2}}}, {"city": {"url": "/", "name": "", "slug": ""}, "name": "Royal Apartments - Apartamenty Inowroc\u0142awska", "img": "http://aff.bstatic.com/images/hotel/max500/739/73986737.jpg", "price_per_day_in_usd": 88, "url": "http://www.booking.com/hotel/pl/royalapartmentswroclaw.html", "country": {"url": "/countries/", "name": "", "slug": ""}, "price": {"PLN": 350, "USD": 88}, "location": {"latitude": 51.114361865662, "longitude": 17.013954520226}, "distance_from_center_in_km": 1.8611177665925, "type": "hotel", "slug": "royal-apartments-apartamenty-inowroclawska-wroclaw", "user": {"distance": {"mi": 0.6, "km": 1}}}, {"city": {"url": "/", "name": "", "slug": ""}, "name": "Art Hotel", "img": "http://aff.bstatic.com/images/hotel/max500/754/75412363.jpg", "price_per_day_in_usd": 91, "url": "http://www.booking.com/hotel/pl/arthotelwroclaw.html", "country": {"url": "/countries/", "name": "", "slug": ""}, "price": {"PLN": 361, "USD": 91}, "location": {"latitude": 51.112174972318, "longitude": 17.029940485954}, "distance_from_center_in_km": 0.76664155249133, "type": "hotel", "slug": "art-hotel-wroclaw", "user": {"distance": {"mi": 0, "km": 0}}}, {"city": {"url": "/", "name": "", "slug": ""}, "name": "Hotel Monopol Wroc\u0142aw", "img": "http://aff.bstatic.com/images/hotel/max500/516/51688584.jpg", "price_per_day_in_usd": 131, "url": "http://www.booking.com/hotel/pl/monopol-wroclaw.html", "country": {"url": "/countries/", "name": "", "slug": ""}, "price": {"PLN": 519, "USD": 131}, "location": {"latitude": 51.106032174134, "longitude": 17.030812203884}, "distance_from_center_in_km": 0.57737237827299, "type": "hotel", "slug": "hotel-monopol-wroclaw-wroclaw", "user": {"distance": {"mi": 0, "km": 0}}}]