[{"city": {"url": "/kosice-slovakia", "name": "Kosice", "slug": "kosice-slovakia"}, "name": "San Domenico caff\u00e9", "price_per_day_in_usd": 0, "url": "http://workfrom.co/san-domenico-caffe", "country": {"url": "/countries/slovakia", "name": "Slovakia", "slug": "slovakia"}, "location": {"latitude": 48.720573486782, "longitude": 21.255599856377}, "distance_from_center_in_km": 0.16838302484538, "type": "coffee", "slug": "san-domenico-caffe-dominikanske-nam-3-masiarska-ulica-kosice"}, {"city": {"url": "/kosice-slovakia", "name": "Kosice", "slug": "kosice-slovakia"}, "name": "HalmiCaffe", "price_per_day_in_usd": 0, "url": "http://workfrom.co/halmicaffe", "country": {"url": "/countries/slovakia", "name": "Slovakia", "slug": "slovakia"}, "location": {"latitude": 48.719267550227, "longitude": 21.258952617645}, "distance_from_center_in_km": 0.21092247573239, "type": "coffee", "slug": "halmicaffe-hlavna-21-halmiho-dvor-kosice"}]